{"00.00":{"pagamento":0,"gratis":24418},"00.30":{"pagamento":0,"gratis":19154},"01.00":{"pagamento":0,"gratis":14705},"01.30":{"pagamento":0,"gratis":12204},"02.00":{"pagamento":0,"gratis":9442},"02.30":{"pagamento":0,"gratis":7719},"03.00":{"pagamento":0,"gratis":6818},"03.30":{"pagamento":0,"gratis":6776},"04.00":{"pagamento":0,"gratis":7570},"04.30":{"pagamento":0,"gratis":9740},"05.00":{"pagamento":0,"gratis":13578},"05.30":{"pagamento":0,"gratis":19453},"06.00":{"pagamento":0,"gratis":27078},"06.30":{"pagamento":0,"gratis":53957},"07.00":{"pagamento":0,"gratis":72608},"07.30":{"pagamento":52073,"gratis":8422},"08.00":{"pagamento":61610,"gratis":8755},"08.30":{"pagamento":71777,"gratis":9741},"09.00":{"pagamento":67639,"gratis":11968},"09.30":{"pagamento":60750,"gratis":14484},"10.00":{"pagamento":65300,"gratis":16781},"10.30":{"pagamento":59090,"gratis":18094},"11.00":{"pagamento":55725,"gratis":17753},"11.30":{"pagamento":53046,"gratis":17588},"12.00":{"pagamento":48289,"gratis":15848},"12.30":{"pagamento":46058,"gratis":14271},"13.00":{"pagamento":43262,"gratis":12744},"13.30":{"pagamento":42376,"gratis":12112},"14.00":{"pagamento":44499,"gratis":12213},"14.30":{"pagamento":45309,"gratis":13261},"15.00":{"pagamento":43447,"gratis":13528},"15.30":{"pagamento":41728,"gratis":14195},"16.00":{"pagamento":41195,"gratis":15056},"16.30":{"pagamento":41875,"gratis":16164},"17.00":{"pagamento":42542,"gratis":16133},"17.30":{"pagamento":43802,"gratis":16741},"18.00":{"pagamento":34073,"gratis":29651},"18.30":{"pagamento":32747,"gratis":28323},"19.00":{"pagamento":30391,"gratis":26738},"19.30":{"pagamento":0,"gratis":73608},"20.00":{"pagamento":0,"gratis":64185},"20.30":{"pagamento":0,"gratis":57067},"21.00":{"pagamento":0,"gratis":48465},"21.30":{"pagamento":0,"gratis":43571},"22.00":{"pagamento":0,"gratis":40292},"22.30":{"pagamento":0,"gratis":37565},"23.00":{"pagamento":0,"gratis":34971},"23.30":{"pagamento":0,"gratis":30411}}